.project
.pydevproject
CHANGES.txt
Contributors.txt
MANIFEST.in
README.txt
paster.ini
setup.cfg
setup.py
docs/conf.py
docs/index.rst
tests/__init__.py
tests/test_widget.py
tw/__init__.py
tw.jqgrid.egg-info/PKG-INFO
tw.jqgrid.egg-info/SOURCES.txt
tw.jqgrid.egg-info/dependency_links.txt
tw.jqgrid.egg-info/entry_points.txt
tw.jqgrid.egg-info/namespace_packages.txt
tw.jqgrid.egg-info/not-zip-safe
tw.jqgrid.egg-info/paster_plugins.txt
tw.jqgrid.egg-info/requires.txt
tw.jqgrid.egg-info/top_level.txt
tw/jqgrid/__init__.py
tw/jqgrid/release.py
tw/jqgrid/samples.py
tw/jqgrid/widgets.py
tw/jqgrid/static/jquery.jqGrid-3.8.1.zip
tw/jqgrid/static/css/jquery.searchFilter.css
tw/jqgrid/static/css/ui.jqgrid.css
tw/jqgrid/static/i18n/grid.locale-en.js
tw/jqgrid/static/i18n/grid.locale-fr.js
tw/jqgrid/static/javascript/jquery.jqGrid.min.js
tw/jqgrid/static/src/JsonXml.js
tw/jqgrid/static/src/grid.base.js
tw/jqgrid/static/src/grid.celledit.js
tw/jqgrid/static/src/grid.common.js
tw/jqgrid/static/src/grid.custom.js
tw/jqgrid/static/src/grid.formedit.js
tw/jqgrid/static/src/grid.grouping.js
tw/jqgrid/static/src/grid.import.js
tw/jqgrid/static/src/grid.inlinedit.js
tw/jqgrid/static/src/grid.jqueryui.js
tw/jqgrid/static/src/grid.loader.js
tw/jqgrid/static/src/grid.postext.js
tw/jqgrid/static/src/grid.setcolumns.js
tw/jqgrid/static/src/grid.subgrid.js
tw/jqgrid/static/src/grid.tbltogrid.js
tw/jqgrid/static/src/grid.treegrid.js
tw/jqgrid/static/src/jqDnR.js
tw/jqgrid/static/src/jqModal.js
tw/jqgrid/static/src/jquery.fmatter.js
tw/jqgrid/static/src/jquery.searchFilter.js
tw/jqgrid/static/src/ui.multiselect.js