Metadata-Version: 1.0
Name: tw.jqgrid
Version: 0.3dev-20110207
Summary: tosca widget wrapper around jqgrid library
Home-page: http://code.google.com/p/twjqgrid
Author: Nicolas Laurance
Author-email: nicolas[dot]laurance[at]gmail[dot]com
License: UNKNOWN
Keywords: toscawidgets.widgets,jquery,grid,jqgrid
Platform: UNKNOWN
Classifier: Development Status :: 4 - Beta
Classifier: Environment :: Web Environment
Classifier: Environment :: Web Environment :: ToscaWidgets
Classifier: Topic :: Software Development :: Libraries :: Python Modules
Classifier: Topic :: Software Development :: Widget Sets
Classifier: Intended Audience :: Developers
Classifier: Operating System :: OS Independent
Classifier: Programming Language :: Python
Classifier: Framework :: TurboGears :: Widgets
Classifier: License :: OSI Approved :: GNU Affero General Public License v3
Classifier: License :: OSI Approved :: MIT License
